fpythonic/circular_array.py
fpythonic_circular_array-4.1.0.dist-info/licenses/LICENSE
fpythonic_circular_array-4.1.0.dist-info/WHEEL
fpythonic_circular_array-4.1.0.dist-info/METADATA
fpythonic_circular_array-4.1.0.dist-info/RECORD
