Metadata-Version: 2.4
Name: fpythonic.circular-array
Version: 4.1.0
Summary: An indexable circular array data structure.
Keywords: circular array,dequeue,pop,push,indexable,auto resizing
Author-email: "Geoffrey R. Scheller" <geoffrey@scheller.com>
Requires-Python: >=3.12
Classifier: Development Status :: 5 - Production/Stable
Classifier: Framework :: Pytest
Classifier: Intended Audience :: Developers
Classifier: License :: OSI Approved :: Apache Software License
Classifier: Operating System :: OS Independent
Classifier: Programming Language :: Python :: 3.13
Classifier: Typing :: Typed
License-File: LICENSE
Requires-Dist: pytest >=8.3.5 ; extra == "test"
Project-URL: Changelog, https://github.com/grscheller/fpythonic-circular-array/blob/main/CHANGELOG.md
Project-URL: Documentation, https://grscheller.github.io/fpythonic/circular-array
Project-URL: Homepage, https://github.com/grscheller/fpythonic/blob/main/README.md
Project-URL: Source, https://github.com/grscheller/fpythonic-circular-array
Provides-Extra: test
